twist_op.py
twist_op-0.2.dist-info/METADATA
twist_op-0.2.dist-info/WHEEL
twist_op-0.2.dist-info/top_level.txt
twist_op-0.2.dist-info/RECORD
