Metadata-Version: 2.1
Name: twist-op
Version: 0.2
Summary: A sample implementation of twist order parameter for a network.
Home-page: https://github.com/vitroid/twist-op/
Author: Masakazu Matsumoto
Author-email: vitroid@gmail.com
License: MIT
Keywords: twist,water,hydrogen bonds,geometry
Platform: UNKNOWN
Classifier: Development Status :: 4 - Beta
Classifier: Intended Audience :: Developers
Classifier: Programming Language :: Python
Classifier: Programming Language :: Python :: 3.5
